piera/__init__.py
piera/backends.py
piera/piera.py
piera-1.2.0.dist-info/METADATA
piera-1.2.0.dist-info/WHEEL
piera-1.2.0.dist-info/top_level.txt
piera-1.2.0.dist-info/RECORD
