Metadata-Version: 2.1
Name: piera
Version: 1.2.0
Summary: a python hiera parser
Home-page: http://github.com/b1naryth1ef/piera
Author: Andrei Zbikowski
Author-email: andrei.zbikowski@gmail.com
License: Apache 2.0
Platform: UNKNOWN
Classifier: Development Status :: 3 - Alpha
Classifier: Intended Audience :: Developers
Classifier: Natural Language :: English
Classifier: License :: OSI Approved :: Apache Software License
Classifier: Programming Language :: Python
Classifier: Programming Language :: Python :: 2.6
Classifier: Programming Language :: Python :: 2.7
Classifier: Programming Language :: Python :: 3.2
Classifier: Programming Language :: Python :: 3.3
Requires-Dist: pyyaml
